wedata/__init__.py
wedata/feature_store/__init__.py
wedata/feature_store/client.py
wedata/feature_store/mlflow_model.py
wedata/feature_store/cloud_sdk_client/__init__.py
wedata/feature_store/cloud_sdk_client/client.py
wedata/feature_store/cloud_sdk_client/models.py
wedata/feature_store/cloud_sdk_client/utils.py
wedata/feature_store/common/__init__.py
wedata/feature_store/common/log/__init__.py
wedata/feature_store/common/log/logger.py
wedata/feature_store/common/protos/__init__.py
wedata/feature_store/common/protos/feature_store_pb2.py
wedata/feature_store/common/store_config/__init__.py
wedata/feature_store/common/store_config/redis.py
wedata/feature_store/constants/__init__.py
wedata/feature_store/constants/constants.py
wedata/feature_store/constants/engine_types.py
wedata/feature_store/entities/__init__.py
wedata/feature_store/entities/column_info.py
wedata/feature_store/entities/environment_variables.py
wedata/feature_store/entities/feature.py
wedata/feature_store/entities/feature_column_info.py
wedata/feature_store/entities/feature_function.py
wedata/feature_store/entities/feature_lookup.py
wedata/feature_store/entities/feature_spec.py
wedata/feature_store/entities/feature_spec_constants.py
wedata/feature_store/entities/feature_table.py
wedata/feature_store/entities/feature_table_info.py
wedata/feature_store/entities/function_info.py
wedata/feature_store/entities/on_demand_column_info.py
wedata/feature_store/entities/source_data_column_info.py
wedata/feature_store/entities/training_set.py
wedata/feature_store/feast_client/__init__.py
wedata/feature_store/feast_client/feast_client.py
wedata/feature_store/feature_table_client/__init__.py
wedata/feature_store/feature_table_client/feature_table_client.py
wedata/feature_store/spark_client/__init__.py
wedata/feature_store/spark_client/spark_client.py
wedata/feature_store/training_set_client/__init__.py
wedata/feature_store/training_set_client/training_set_client.py
wedata/feature_store/utils/__init__.py
tencent_wedata_feature_engineering-0.1.40.dist-info/METADATA
tencent_wedata_feature_engineering-0.1.40.dist-info/WHEEL
tencent_wedata_feature_engineering-0.1.40.dist-info/top_level.txt
tencent_wedata_feature_engineering-0.1.40.dist-info/RECORD
