Metadata-Version: 2.1
Name: tencent-wedata-feature-engineering
Version: 0.1.40
Summary: Wedata Feature Engineering Library Development
Home-page: 
Author: meahqian
Author-email: 
License: Apache 2.0
Classifier: Programming Language :: Python :: 3
Classifier: License :: OSI Approved :: Apache Software License
Classifier: Operating System :: OS Independent
Requires-Python: >=3.7
Requires-Dist: pandas>=1.0.0
Requires-Dist: feast[redis]==0.49.0
Requires-Dist: grpcio==1.74.0
Requires-Dist: tencentcloud-sdk-python
Requires-Dist: ipython
